CHANGELOG.rst
LICENSE
MANIFEST.in
Makefile
README.rst
setup.py
docs/api.rst
docs/changelog.rst
docs/cli.rst
docs/conf.py
docs/index.rst
docs/installation.rst
docs/intro.rst
najdisi_sms/__init__.py
najdisi_sms/api.py
najdisi_sms/cli.py
najdisi_sms/utils.py
najdisi_sms.egg-info/PKG-INFO
najdisi_sms.egg-info/SOURCES.txt
najdisi_sms.egg-info/dependency_links.txt
najdisi_sms.egg-info/entry_points.txt
najdisi_sms.egg-info/not-zip-safe
najdisi_sms.egg-info/requires.txt
najdisi_sms.egg-info/top_level.txt
tests/__init__.py
tests/fixtures/cassettes/LoadTestCase.test_dummy.json