Metadata-Version: 1.1
Name: najdisi-sms
Version: 1.0.2
Summary: Najdi.si sms command line tool and API
Home-page: https://github.com/brodul/najdi-si-sms
Author: Domen Kozar, Andraz Brodnik
Author-email: brodul@brodul.org
License: BSD
Keywords: development notification sms gateway najdi telekom slovenia
Platform: UNKNOWN
Classifier: Development Status :: 3 - Alpha
Classifier: Intended Audience :: Developers
Classifier: Intended Audience :: System Administrators
Classifier: Topic :: Communications :: Telephony
Classifier: Topic :: System :: Logging
Classifier: License :: OSI Approved :: BSD License
Classifier: Programming Language :: Python :: 2
Classifier: Programming Language :: Python :: 2.7
Classifier: Programming Language :: Python :: 3
Classifier: Programming Language :: Python :: 3.3
Classifier: Programming Language :: Python :: 3.4
